scriptmonkey/__init__.py
scriptmonkey/__main__.py
scriptmonkey/core.py
scriptmonkey/utils/__init__.py
scriptmonkey/utils/file_handler.py
scriptmonkey/utils/tree.py
scriptmonkey-2.0.1.dist-info/METADATA
scriptmonkey-2.0.1.dist-info/WHEEL
scriptmonkey-2.0.1.dist-info/entry_points.txt
scriptmonkey-2.0.1.dist-info/top_level.txt
scriptmonkey-2.0.1.dist-info/RECORD
