Metadata-Version: 2.1
Name: scriptmonkey
Version: 2.0.1
Summary: A simple CLI utility for copying files and directory trees to clipboard for easy sharing with LLMs.
Home-page: https://github.com/lukerbs/ScriptMonkey
Author: Luke Kerbs
Author-email: LDK.kerbs@gmail.com
License: MIT
Keywords: clipboard,file sharing,directory tree,development tools,python tools,LLM helper,code sharing,project structure,file utility,developer tools
Classifier: Programming Language :: Python :: 3
Classifier: License :: OSI Approved :: MIT License
Classifier: Operating System :: OS Independent
Requires-Python: >=3.6
Requires-Dist: rich
Requires-Dist: pyperclip
